bygul/__init__.py
bygul/_cli.py
bygul/utils.py
bygul-2025.4.dist-info/METADATA
bygul-2025.4.dist-info/WHEEL
bygul-2025.4.dist-info/entry_points.txt
bygul-2025.4.dist-info/top_level.txt
bygul-2025.4.dist-info/RECORD
