Metadata-Version: 2.4
Name: bygul
Version: 2025.4
Summary: Amplicon read simualtor
Home-page: https://github.com/andersen-lab/Bygul
Author: Maryam Ahmadi Jeshvaghane
Author-email: mahmadi@scripps.edu
License: BSD 2-Clause
Requires-Dist: click
Requires-Dist: pandas
Requires-Dist: biopython
Requires-Dist: regex
Requires-Dist: numpy
Dynamic: author
Dynamic: author-email
Dynamic: description
Dynamic: description-content-type
Dynamic: home-page
Dynamic: license
Dynamic: requires-dist
Dynamic: summary
